kxy/__init__.py
kxy/api/__init__.py
kxy/api/client.py
kxy/api/data_transfer.py
kxy/api/decorators.py
kxy/api/utils.py
kxy/billing/__init__.py
kxy/billing/billing_details.py
kxy/finance/__init__.py
kxy/finance/corr.py
kxy/learning/__init__.py
kxy/learning/base_learners.py
kxy/learning/leanml_predictor.py
kxy/learning/pytorch_early_termination.py
kxy/learning/shrunk_learner.py
kxy/learning/tensorflow_early_termination.py
kxy/misc/__init__.py
kxy/misc/boruta.py
kxy/misc/examples.py
kxy/misc/exceptions.py
kxy/misc/mind.py
kxy/misc/naive.py
kxy/misc/predictors.py
kxy/misc/rfe.py
kxy/misc/tf/__init__.py
kxy/misc/tf/config.py
kxy/misc/tf/generators.py
kxy/misc/tf/initializers.py
kxy/misc/tf/layers.py
kxy/misc/tf/learners.py
kxy/misc/tf/losses.py
kxy/misc/tf/models.py
kxy/misc/tf/ops.py
kxy/pandas_extension/__init__.py
kxy/pandas_extension/accessor.py
kxy/pandas_extension/base_accessor.py
kxy/pandas_extension/features_accessor.py
kxy/pandas_extension/features_utils.py
kxy/pandas_extension/finance_accessor.py
kxy/pandas_extension/learning_accessor.py
kxy/pandas_extension/post_learning_accessor.py
kxy/pandas_extension/pre_learning_accessor.py
kxy/pfs/__init__.py
kxy/pfs/pfs_predictor.py
kxy/pfs/pfs_selector.py
kxy/post_learning/__init__.py
kxy/post_learning/improvability.py
kxy/post_learning/model_explanation.py
kxy/pre_learning/__init__.py
kxy/pre_learning/achievable_performance.py
kxy/pre_learning/variable_selection.py
kxy-1.4.11.data/scripts/kxy
kxy-1.4.11.dist-info/LICENSE
kxy-1.4.11.dist-info/METADATA
kxy-1.4.11.dist-info/WHEEL
kxy-1.4.11.dist-info/top_level.txt
kxy-1.4.11.dist-info/RECORD
